{
  "scan_time": "2026-03-06T01:35:46.698574Z",
  "mode": "search",
  "account_signals": [],
  "search_signals": [
    {
      "platform": "x",
      "author": "DegenWar01",
      "tier": "unknown",
      "text": "2x pump on my alpha call on $HUMAN CA>> 9f8PBfqPVap88ijxpVtssbQSUL7ZxiQj8thq3tmApump #memecoin #solana #Degen",
      "likes": 0,
      "retweets": 0,
      "replies": 0,
      "views": 0,
      "engagement_score": 0,
      "engagement_rate": 0,
      "tweet_id": "2029730945247420742",
      "url": "https://x.com/DegenWar01/status/2029730945247420742",
      "created_at": "",
      "scanned_at": "2026-03-06T01:35:46.698574Z"
    }
  ],
  "summary": {
    "total_signals": 1,
    "search_signals": 1
  }
}