{
  "Come Back Dad": {
    "posts": [
      {
        "id": "7627886968512187661",
        "v": 1135,
        "l": 87,
        "s": 28,
        "cap": "\"I keep waiting for Spence to leave. Because I can't wrap my mind around why he would stay. Because you didn't.\". Tatyana Ali and Charles S. Dutton. Come Back Dad. Streaming free on VURT. @tatyanaali  #VURT #ComeBackDad #TatyanaAli #CharlesSDutton #DramaTok  "
      },
      {
        "id": "7626763852465605901",
        "v": 909,
        "l": 105,
        "s": 5,
        "cap": "\"I got straight A's. I got awards. I got accepted into one of the finest medical institutions in this nation. And my father complained the whole time about you.\". Some wounds go all the way back.. Come Back Dad. Streaming free on VURT. Myvurt.com #VURT #ComeBackDad #DramaTok #FamilyDrama "
      }
    ],
    "clips": [
      {
        "name": "Comeback-1.mp4",
        "fid": "ad9ed1ea-c236-4797-ad55-48f83bd1d47c",
        "dur": 46,
        "txt": "No, you fail every day. You know, you hated me since we were little. Yes, I have. I got straight A's. I got awards. I got accepted into one of the finest medical institutions in this nation. And my father complained the whole time about you. He couldn't even acknowledge our accomplishments without saying that he was glad that they were not your failures. You were his beloved project. He reveled in your dysfunction. The tortured artiste. Well, we worked hard for his love, and he showered you with it. Oh, Daddy hated me, and you know it. He didn't hate you."
      },
      {
        "name": "ComeBack-2.mp4",
        "fid": "f37eb0e5-945f-4fa0-bba6-9b684e2ef867",
        "dur": 26,
        "txt": "What about when I paid for you to go back to school 10 years ago and you quit? What about when I paid for your first car? You were too cheap to pay for the insurance. What about when I paid for the bulk of your wedding to my best friend? Jeanette was my best friend and you ruined it."
      },
      {
        "name": "VURT_COMEBACKDAD_Social 01.mp4",
        "fid": "966ffd71-9fd4-4242-980a-fb3279acd280",
        "dur": 70,
        "txt": ""
      },
      {
        "name": "VURT_COMEBACKDAD_Social 02_1.mp4",
        "fid": "e9be066c-a4e7-4972-9c09-128bf1df6248",
        "dur": 68,
        "txt": "Showing up to gigs drunk. I punched a guy in the audience, Odell. He was heckling me, man. He was clapping, O. Look, I need this, Benny. I'm clean. How long? 2 months, 4 days, and 7 and a half hours. Oh. I'm rooting for you more than anybody. But you gotta prove you can be a reliable musician, man. Yeah, we got another spot for a piano player, but I can only give it to someone who's gonna show up on time, come to rehearsal without a bottle in his hand, and not throw up during a set, brother. It happened once. It was on the bass player."
      },
      {
        "name": "VURT_COMEBACKDAD_Social 05_1.mp4",
        "fid": "2ca1673a-accb-4b41-8398-9bd4e4ae2b15",
        "dur": 68,
        "txt": "The bride's father, Mr. Othello Babineaux. [FOREIGN LANGUAGE]"
      },
      {
        "name": "VURT_COMEBACKDAD_Social 03_1.mp4",
        "fid": "8cca91fc-abc5-492b-9985-2523840cb0d9",
        "dur": 70,
        "txt": ""
      },
      {
        "name": "VURT_COMEBACKDAD_Social 04.mp4",
        "fid": "9baaaee8-84ff-4933-b040-649c881794c1",
        "dur": 61,
        "txt": "It's been, you know, it's been a while. See, most of the time I like fix cars, and so it's been a while. Stop wasting my time."
      }
    ]
  },
  "Favorite Son": {
    "posts": [
      {
        "id": "7631208180156075277",
        "v": 283,
        "l": 19,
        "s": 3,
        "cap": "When your father announces your future at dinner. And calls it destiny. Favorite Son. A VURT Premiere. Streaming free on VURT. @Jonathan McReynolds @Rotimi @Serayah @LorenSharice @Anton Peeples  #FavoriteSon #VURT #MicroDrama #ChurchDrama #GospelDrama"
      },
      {
        "id": "7630840412378320142",
        "v": 295,
        "l": 16,
        "s": 1,
        "cap": "\"I thought we were trying to wait till marriage.\". The rule a pastor's son makes. The one a pastor's son breaks. Favorite Son. Free on VURT. @Serayah @Rotimi @Jonathan McReynolds @LorenSharice @Anton Peeples @Anthony Evans  #VURT #FavoriteSon #BlackCinema #ChurchTok #DramaTok "
      },
      {
        "id": "7630479241242512653",
        "v": 982,
        "l": 30,
        "s": 4,
        "cap": "\"I am more than your party planner. I am your wife.\" When the church becomes the other woman. Tank and Lisa Arrindell in Favorite Son Christmas. Free on VURT. @Dr. Durrell \"Tank\" Babbs Sr. @Rotimi  #VURT #FavoriteSon #FirstLady l #ChurchDrama "
      }
    ],
    "clips": [
      {
        "name": "VURT_FavoriteSon_Social_Edit_001-v2.mp4",
        "fid": "92cbf726-e74e-43a8-b4e0-23b4057c6cfa",
        "dur": 40,
        "txt": "Uh, we shouldn't. Yeah, you're right. Or we could skip dinner and\u2014 I thought we were trying to wait till\u2014 Till marriage? Are you gonna let me in on when that's gonna be?"
      },
      {
        "name": "VURT_FavoriteSon_Social_Edit_004-v2.mp4",
        "fid": "b3c999a2-2732-4d05-b026-101561b469a7",
        "dur": 85,
        "txt": "I know you have responsibilities. So do I. But constantly covering for you not showing up shouldn't be one of them. So I missed your little meeting. Oh, don't do that. I will make the next one. You promised me no matter what that you would prioritize home first. I am sick of you putting the church and her before me. I didn't sign up for that. And after all these years\u2014 You know what I do. You know when I'm not here, I am taking care of business, trying to expand while keeping us and the church afloat. Yes, I know what you do. And you need to figure out a better way. Because if you don't\u2014 Rita. I need you to show up for us! Billy! I need you to be where I need you to be! I am more than your party planner and your little organizer. I am your wife, and you will respect me, and you will put your family first."
      },
      {
        "name": "VURT_FavoriteSon_Social_Edit_002.mp4",
        "fid": "090d9bdf-5d85-45ce-bad8-b7df820bc930",
        "dur": 52,
        "txt": "Dad. Right here. What happened tonight better not ever happen again. You hear me? You sure voted for Royce London. I wasn't. Of course you did. That's my church. You hear me? You play what I tell you to play. And you do what I tell you to do."
      },
      {
        "name": "VURT_FavoriteSon_Social_Edit_003.mp4",
        "fid": "c2a7f84c-cd51-4fa1-a1d1-125c3c0ca9df",
        "dur": 72,
        "txt": "So, Cam, you'll update your dad on all the talking points then? Yes, ma'am. I'll let him know. The Foundation would also like for the entire family to stick around for for a group photo with the volunteers after So Gifted performs. Yes, of course. Great. I will give them a call and follow up with the caterers. Is there anything else for Sadie? Oh, no, Regina. Thank you. Oh, just update the rest of the fundraising committee for me. You got it. Thank you. Baby, you okay? You look tired. Yeah. Late night. Just working on some new songs. Oh. Workaholic, just like your daddy. He stayed overnight studying in his office again. Oh."
      },
      {
        "name": "VURT_FavoriteSon_Social_Edit_005.mp4",
        "fid": "fcd30bf4-de0f-4a84-ad90-75db1a562607",
        "dur": 54,
        "txt": "He's going to change the face of gospel. Mm-hmm. Pastors the church in Houston for me. Mm-hmm. Oh, I didn't realize you finalized plans, Dad. When you opening it? Oh, it'll be at least a year from now. I'm going to start with online services weekly from here, and then Blaine He's gonna move to Houston and run it all. Praise the Lord. Both of our sons walking into their destinies. Amen."
      }
    ]
  },
  "Karma in Heels": {
    "posts": [
      {
        "id": "7623140703396236557",
        "v": 189600,
        "l": 144,
        "s": 23,
        "cap": "\"You did this to me\" \u2014 and she meant every word of it. Just not the way he thinks. Karma in Heels. Free on VURT. myvurt.com @snooperstar  #VURT #KarmainHeels #Microdrama #Drama #FreeStreaming "
      },
      {
        "id": "7622714115051556109",
        "v": 315,
        "l": 14,
        "s": 0,
        "cap": "\"He doesn't know the new you from a can of paint.\" She's not asking. She's telling her to finish what she started. Karma in Heels. Free on myvurt.com @snooperstar #VURT #KarmainHeels #Microdrama #Dramatok #FreeStreaming #IndieFilm"
      },
      {
        "id": "7622364562645355789",
        "v": 307,
        "l": 11,
        "s": 0,
        "cap": "The voice in her head already picked him. He just doesn't know it yet. Karma in Heels. Free on VURT. Link in bio. @snooperstar  #VURT #KarmaInHeels #MicroDrama #DramaTok #IndieFilm"
      },
      {
        "id": "7622049910602485006",
        "v": 24,
        "l": 2,
        "s": 0,
        "cap": "\"I got a surprise for you. Better than this old thing.\" \u2026Tyler should've left when she said wait. @snooperstar myvurt.com #VURT #KarmainHeels #Microdrama #Dramatok #FreeStreaming  #IndieFilm"
      }
    ],
    "clips": [
      {
        "name": "KARMA_IN_HEELS_SocialEdit_001-v3.mp4",
        "fid": "682257cb-9bb1-4fad-83ac-bc68660cef78",
        "dur": 24,
        "txt": "So you saying if I pledge, everything on the table for me, but if I don't pledge, everything off the table? Bingo. That simple. And back to the hood you go without an offer."
      },
      {
        "name": "KARMA_IN_HEELS_SocialEdit_002-v3.mp4",
        "fid": "bddaea09-ed19-4239-aad3-42a499d738db",
        "dur": 27,
        "txt": "Back after introduction. I see you tonight. I booked everything. I'mma send you the information. Okay. I can't believe I'm about to lose my virginity to the man of my dream."
      },
      {
        "name": "KARMA_IN_HEELS_SocialEdit_003-v3.mp4",
        "fid": "dea60fd2-06ba-47b0-94ed-d2745176cb15",
        "dur": 30,
        "txt": "What the fuck? You, you did this to me. You did this to me. Our special night, I was just a game. You did this to me. I was just a toy on your initiation night. Charisma, what are you talking about? I hate you. Charisma!"
      },
      {
        "name": "KARMA_IN_HEELS_SocialEdit_004-v3.mp4",
        "fid": "08d6504c-cdaf-4e40-8761-6c8b9495fcc0",
        "dur": 24,
        "txt": "Oh, and I'm feeling you. Feeling me? You don't even know me. You see that smile? That shit is so sexy, baby. Why are you following me? What do you want from me? I just want to get to know you."
      },
      {
        "name": "KARMA_IN_HEELS_SocialEdit_005-v3.mp4",
        "fid": "94463783-68ba-4623-8e32-d791f42bb57f",
        "dur": 25,
        "txt": "And you! Your stupid brother and your stupid fraternity friends made a complete mockery of me! Wait\u2014 no... No, don't be so surprised Tyler! I got a surprise for you better than this old thing."
      },
      {
        "name": "KARMA_IN_HEELS_SocialEdit_006-v3.mp4",
        "fid": "83656251-3e2a-475c-a359-791459bc4e74",
        "dur": 27,
        "txt": "You came here to do a job. He doesn't know the new you from a can of paint. Okay? I need you to own this shit. Yeah? Okay."
      },
      {
        "name": "KARMA_IN_HEELS_SocialEdit_007-v3.mp4",
        "fid": "8c1e7701-0730-40bb-baf7-ff8a8081c8a0",
        "dur": 21,
        "txt": "Fuck outta here. You gonna feel this shit, every inch. And you better remember every fucking thing they did to you."
      },
      {
        "name": "KARMA_IN_HEELS_SocialEdit_008-v3.mp4",
        "fid": "241b93d0-0214-48e5-8514-8589ccd76754",
        "dur": 27,
        "txt": "You're telling me that the man that raped you was standing on that podium preaching and you're catching the Holy Ghost? Quit. Go back."
      },
      {
        "name": "KARMA_IN_HEELS_SocialEdit_009-v3.mp4",
        "fid": "24fec351-343f-4244-bad2-69db2fec41c1",
        "dur": 28,
        "txt": "I know we already getting this party started without me, sister. I would never. I wanna play. Especially with this motherfucker. Who are you talking to? Leave me alone!"
      },
      {
        "name": "KARMA_IN_HEELS_SocialEdit_010-v3.mp4",
        "fid": "c9e404aa-d99a-4707-88c8-145206f7089c",
        "dur": 34,
        "txt": "Wow! Welcome to the Eta Chi Psi grad chapter sisterhood. My goodness, girl, you are gorgeous. Well, thank you so much. Yes, it's giving like melanin goddess. Not like you already. So sign your name here, put your contact information, and we're going to take you into the intake room."
      }
    ]
  },
  "The Parking Lot Series": {
    "posts": [
      {
        "id": "7630149211333381389",
        "v": 105,
        "l": 0,
        "s": 0,
        "cap": "Catch up before the new episode drops today \ud83d\udc40 The Parking Lot. Free on VURT. #VURT #TheParkingLot #MicroDrama #DramaTok #IndieFilm"
      },
      {
        "id": "7625407462069374221",
        "v": 118,
        "l": 2,
        "s": 1,
        "cap": "The audience voted to handle it themselves. Now somebody's gone. The Parking Lot Series. Interactive series. Free on VURT. Myvurt.com @JAM\u00c0LY  #VURT #TheParkingLot #MicroDrama #DramaTok #IndieFilm"
      },
      {
        "id": "7625021341640494349",
        "v": 122,
        "l": 2,
        "s": 1,
        "cap": "Jason already took one of them. Now he's close to finding what they've all been looking for. They have to get there first. The Parking Lot. You decide what happens next. Free on VURT. Myvurt.com @JAM\u00c0LY  #VURT #TheParkingLot #MicroDrama #DramaTok #IndieFilm"
      },
      {
        "id": "7624260565103299854",
        "v": 818,
        "l": 4,
        "s": 0,
        "cap": "She said leave. He called Alicia instead. Now his boy's reaching under the seat. The Parking Lot. Free on myvurt.com @JAM\u00c0LY  #VURT #TheParkingLot #MicroDrama #DramaTok #IndieFilm"
      },
      {
        "id": "7623882992464809230",
        "v": 324,
        "l": 6,
        "s": 0,
        "cap": "The director said it himself. The Parking Lot is streaming free on VURT. @JAM\u00c0LY  #VURT #TheParkingLot #MicroDrama #DramaTok #IndieFilm"
      },
      {
        "id": "7623531176036175117",
        "v": 307,
        "l": 2,
        "s": 0,
        "cap": "She told him to leave. He should've never come back. The Parking Lot. Streaming free on VURT. myvurt.com @JAM\u00c0LY  #VURT #TheParkingLot #MicroDrama #dramatok #indiefilm "
      }
    ],
    "clips": [
      {
        "name": "PARKING_LOT-Ep02-_Social Edit-002-v2.mp4",
        "fid": "b640e6f3-3748-4951-a345-5d84fbf82605",
        "dur": 30,
        "txt": "You're kidding! Ah, success! Sometimes that's all it takes. What's wrong?"
      },
      {
        "name": "PARKING_LOT-Ep05-_Social Edit-004-v2.mp4",
        "fid": "f7e3dd6c-1273-4201-bac5-adea9084605a",
        "dur": 42,
        "txt": "Man, Alicia shouldn't be the only one losing sleep over this. Then don't make it worse. Worse? Nigga, you think I give a fuck about making it worse? This nigga made it worse when he called Alicia. Let me go get this gas, man. Make it worse."
      },
      {
        "name": "PARKING_LOT-Ep07-_Social Edit-008-v2.mp4",
        "fid": "2e9a8962-dd85-400b-90c1-168284b9edf8",
        "dur": 44,
        "txt": "What's wrong? What? Jason! We got bigger fish to fry than that, Terrence. The shit!"
      },
      {
        "name": "PARKING_LOT-Ep01-_Social Edit-001-v1.mp4",
        "fid": "9356ff30-4d7f-4c7c-a62a-2d36d8facee2",
        "dur": 35,
        "txt": ""
      },
      {
        "name": "PARKING_LOT-Ep04-_Social Edit-003-v1.mp4",
        "fid": "267b779c-3bc7-4e50-a282-07f35ce9d609",
        "dur": 24,
        "txt": "So who is this dude? I told you what happened. You said that somebody fixed your car, then called you later and knew things that they shouldn't. That ain't no story, that's a fucking problem. Chill, relax."
      },
      {
        "name": "PARKING_LOT-Ep07-_Social Edit-005-v1.mp4",
        "fid": "6c1c042d-b7bc-420a-a819-da7107ff71e3",
        "dur": 23,
        "txt": "Leave! Sit!"
      },
      {
        "name": "PARKING_LOT-Ep06-_Social Edit-006-v1.mp4",
        "fid": "a1a2e9c4-5b2a-4741-9999-025fb713b06a",
        "dur": 29,
        "txt": "You been following her? Nah, I'm waiting. Waiting for what? I'm waiting for the truth to come up. Nah, nigga, don't go nowhere, nigga. Don't go nowhere."
      },
      {
        "name": "PARKING_LOT-Ep08-_Social Edit-007-v1.mp4",
        "fid": "47f18bc9-201d-48f8-8030-58e9b603e837",
        "dur": 17,
        "txt": ""
      }
    ]
  },
  "The Love Network Jam": {
    "posts": [
      {
        "id": "7630642412288757006",
        "v": 138,
        "l": 2,
        "s": 0,
        "cap": "POV: you're about to kiss your crush and then your homie's face appears. Izzo is all of us. Rue is every friend who's witnessed too much. The Love Network Jam \u2014 Africa's first vertical drama, streaming free on VURT. @BinyumaTV @Ruyonga @Isaac Khaweka  #VURT #TheLoveNetworkJam #BinyumaTV #POV #DaydreamFail  "
      },
      {
        "id": "7630219791973879054",
        "v": 113,
        "l": 0,
        "s": 0,
        "cap": "\"Izzo doesn't listen. That's where all the madness begins.\" Meet Rue. The connector who tried to warn him. The Love Network Jam. Africa's first vertical drama. Free on VURT. #VURT #LoveNetworkJam #AfricanCinema #KampalaCinema #VerticalDrama"
      },
      {
        "id": "7629858185804795150",
        "v": 302,
        "l": 8,
        "s": 0,
        "cap": "All because he tried to do the right thing. \"If you see again, you die. Slowly.\" The Love Network Jam. Free on VURT. @BinyumaTV @Ruyonga @Isaac Khaweka  #VURT #TheLoveNetworkJam #MicroDrama #DramaTok #Kampala"
      },
      {
        "id": "7629108105950825742",
        "v": 121,
        "l": 6,
        "s": 0,
        "cap": "He found her phone. He was just trying to return it. Now he's not going home. The Love Network Jam. Africa's first vertical drama. Streaming free on VURT. @Isaac Khaweka @Ruyonga @BinyumaTV  #VURT #TheLoveNetworkJam #MicroDrama #AfricanCinema #VerticalDrama "
      },
      {
        "id": "7628746332307459341",
        "v": 116,
        "l": 4,
        "s": 1,
        "cap": "One phone. One favor. Now the car's gone too. And she's at the salon like nothing happened. The Love Network Jam. Africa's first vertical drama. Stream free at myvurt.com @BinyumaTV  #VURT #TheLoveNetworkJam #BinyumaTV #VerticalDrama #DramaTok   "
      },
      {
        "id": "7628373009564306701",
        "v": 101,
        "l": 2,
        "s": 0,
        "cap": "Izzo didn't listen. Now look who's paying for it. The Love Network Jam. Streaming free on VURT. @BinyumaTV  #VURT #TheLoveNetworkJam #AfricanCinema #IndieFilm #DramaTok "
      },
      {
        "id": "7627492933717019917",
        "v": 134,
        "l": 3,
        "s": 0,
        "cap": "We\u2019re making history. \ud83c\udf0d We\u2019re premiering the world\u2019s first African original vertical drama, an industry first that shifts the way stories are told and shared across the globe. We are excited to announce that \u201cThe Love Jam Network\u201d is coming soon to myvurt.com  This isn\u2019t just another movie premiere. We are creating pathways for creators everywhere to reach audiences on their own terms. We\u2019re excited to premiere @BinyumaTV from writer @Ruyonga .   If  you're a filmmaker with a story to tell, VURT is built for you. Submit your film. Be live in 48 hours. Create. Submit. Engage. #VURT #IndieFilm #VerticalVideo #Filmmakers #ShortForm   "
      }
    ],
    "clips": [
      {
        "name": "ru.mp4",
        "fid": "692c94ec-a818-4838-86a4-d6e7fa487f38",
        "dur": 197,
        "txt": "What's up? My name is Ryonga, aka Roo. Real bad man. I'm an actor, I'm a rapper, I'm a singer-songwriter. I play Roo on The Love Network. Roo is a connector. He's what some would call a fixer or a handler. Roo knows everyone, up top, in the middle, at the bottom. Ru is an everyman's man. This man! Everyone likes him. Everyone knows him. Sometimes it's to his benefit. Sometimes it's not. You get it? He happens to be one of the best friends of Izo, Ezekiel, played by Izo Isaac. A lot of people have their names around here. Essi is Essi. Ru is Ru. Izo is Izo. Ru and Prince are Izo's friends. Ru wants to connect his people and take them up the ladder, but he feels like he wants to teach them how to to observe protocol, and Izo doesn't have time for that stuff. For him, he's just trying to jump the ladder. So it really begins with him trying to let him know, with Roo trying to let Izo know that that person is not your level. And when Izo doesn't listen, he gets in trouble, and that's where all the madness begins. That's where the Love Network jam just kicks off. Um, I'm a producer on this project. Shout out to Benjima TV, along with a few other people. I bumped into verticals a few months ago. I realized I'd been watching them and watching them, and I was like, eh, number one, what are these things? Then I found out they were verticals. And number two, I've never seen an African vertical yet. I feel like so many Africans are watching them. What's that about? And I think going down that rabbit hole led me to be in a place where we put together a platform, and we're doing the first\u2014 one of the first, if not the first\u2014 vertical movie in Africa with African content. Basically, you call it the first TikTok movie, not just a clip with multiple clips that make up a movie. Benyama TV is a platform that is going to allow creatives to expand their horizons, try out, you know, material, try out and conceptualize\u2014 more than conceptualize, manifest and materialize their ideas without waiting for a big budget. I'm a fan of the Solos, the Primes, the Mama Peshis who do these short-form movies on TikTok. And I'm like, if you lengthen them a bit, you could basically be doing verticals. So what we did is we put together a platform that is going to showcase African creativity, African verticals, African storytelling, African stories, African movies, where we figure it out and we do it on our budget, just like all these TikTokers have been doing, making incredible content. But you will also get paid from it. But that is a whole other story and a whole other discussion we will have when the time is right. But right now, be on the lookout for The Love Network. Now I'm coming to your screens, like right now. My name is Edwin Ryonga. I play Roo on The Love Network. Kaache on Binyamati."
      },
      {
        "name": "Felicity.mp4",
        "fid": "e345d2ab-65c8-4c81-bec5-192941f2d61e",
        "dur": 141,
        "txt": "My name is Felicity Mandela, and I play the character Denise in Love Network. This is a vertical, first of its kind, and the story is about urban crime. You know how, um, day to day there's different things that go on about our lives, but now this is giving perspective of an urban crime story from Africa and how everything is running around. And this lady, this young lady, has power, but you'll be surprised what looks like a coincidence or what looks like an honest mistake of forgetting unruffles everyone's world just to get back a small gadget. So I love the story. Everybody's rattled just to get a small gadget. Yes. Verticals are the new future, and this being the first of its kind happening here is a very good thing because society now is living their life on the phone. And so what verticals have come to do is have your entertainment on the go anywhere you are. You don't have to wait to go to, you know, the cinema or go home to watch a movie. It's now right here on the phone. So I actually appreciate that, that you don't have to overthink it. Have entertainment on the go. [MUSIC] Benyuma TV is the first of its kind here in Africa, and it's focusing on verticals, but specifically showing and telling African stories by Africans, made by Africans, to the world. So we're not having our stories being told for us, but this time around we're telling our own stories, showing you our perspective. From us. Yes, so that's what Benyuma TV is all about. It's merging different African stories told by Africans to the world. My name is Felicity Mandela. Catch me on Benyuma TV."
      },
      {
        "name": "Essy.mp4",
        "fid": "5148b2a0-0d51-4330-8b28-2acace207780",
        "dur": 125,
        "txt": "Hello, SB360! My name is Mahoro Esther. I am an actress, I am a host, I am a content creator, but for this particular project, I am acting as Effie. So this story revolves around a phone. There is this very beautiful boss babe that loses a phone. And the guy that has a crush on her tries to get the phone back to her, but in the process, he encounters a lot of difficulties. He's abducted, he's kidnapped, he's threatened. He finds himself in a position where he's supposed to work with a thief to catch a thief. And he's also working with a group of guys that are helping him. So he eventually\u2014 I don't know if he eventually\u2014 we don't know if he eventually gets the phone to her. You just have to watch the story. You know what happens. It's a movie that is shot like this instead of this, and it's usually for smartphone consumers, you know, because people don't want to first go to their homes, turn on the TVs to watch movies. Right now you can just watch those verticals on your phone without even having to rotate it. Binyuma TV is a platform that's going to stream vertical movies, the first of its kind, I must say, in Africa. So think Netflix, but for vertical movies, okay? Vertical movies from Africa. So there's going to be a lot of genres on there. There's going to be drama, comedy, thrillers, political movies, all sorts of genres. My name is Mahoro Esther. I play Essie on The Love Network, Tachitumbi. [MUSIC] [MUSIC]"
      },
      {
        "name": "Eezo.mp4",
        "fid": "fd8a7f1d-3a8b-451e-87c0-027831135fc7",
        "dur": 161,
        "txt": "Pretty little African girl, girl, you are the queen, you are my world. My name is Isaac Haweka. I am an artist. I do sing, write, perform music. I do perform poetry and write it as well. And right here on this one, I am an actor. That's why I want to call myself an artist. On The Love Network, I play Izo, a go-getter. He's a hustler. He chases paper and he's a dreamer. He dreams quite big on, uh, on business and making it, chasing the bag, but also dreams so much in love life. So he chases love but also chases money and does everything in his power to, to get what he wants. Yes, I've bumped into verticals on social media, on Instagram, and Shorts on YouTube. Instagram, I've\u2014 most of the verticals I've landed on are from Korea, um, some are from the States, yet others, uh, it's Korea in Asia. Yeah, most of them are Asian. I've seen some American, and I've also seen some Spanish, Spanish verticals, but mostly on Instagram and Shorts of YouTube. I'm very excited because Africans hadn't embraced this, but I mean, whether I like it or not, that's where we headed. So the earlier Africa gets on it, the better for entertainment. Benyuma TV is a vertical platform. It's an online platform that is more like a hub for African content, which is in vertical, something that has not been the usual. I haven't seen any in Uganda, not any in East Africa. I haven't seen any in Africa. So this should be the very first one, vertical platform for this kind of content. My name is Isaac Haweka, AKA Izo Wekzi, and I play Izo on The Love Network. Catch it. On Benyuma TV."
      },
      {
        "name": "VURT_Love Network Jam_IG Clip 2.mp4",
        "fid": "a05a5bd7-f1b2-426f-95be-01bc2bdf2e1b",
        "dur": 22,
        "txt": "Be ready to move. Okay. Aha. Who is this?"
      },
      {
        "name": "VURT_Love Network Jam_IG Clip 5.mp4",
        "fid": "b1af8b87-b0ee-40ca-8292-1f5188261c37",
        "dur": 30,
        "txt": "Explain to me again how we have a problem. Really? You want to repeat what I just went through? Exactly what you went through because of your stupid decision. So explain to me how this is a we thing. Stupid? It was your idea. My what? You already look like a thief, Iso. Iso, you keep running in dogs and you don't learn. Stop hitting me. Throw me one mixtape. Iso, do not pick that. Iso, I swear if you pick that phone\u2014 Hello?"
      },
      {
        "name": "VURT_Love Network Jam_IG Clip 4.mp4",
        "fid": "baf0cc35-e39d-4ad4-95c4-86d044f40d52",
        "dur": 36,
        "txt": "Kwa hivyo mslu? Kwa hivyo mslu? Kwa hivyo mslu? mslu? Kwa hivyo mslu? Kwa hivyo mslu? Kwa hivyo mslu? Kwa hivyo mslu? Kwa hivyo mslu? Kwa hivyo mslu? Kwa hivyo mslu? Kwa hivyo mslu? Kwa hivyo mslu?"
      },
      {
        "name": "VURT_Love Network Jam_IG Clip 5 (subtitles).mp4",
        "fid": "c1d61108-849b-4fcc-b5cb-5461e2b27091",
        "dur": 30,
        "txt": "Explain to me again how we have a problem. Really? You want to repeat what I just went through? Exactly what you went through because of your stupid decision. So explain to me how this is a we thing. Stupid? It was your idea. My what? You already look like a thief, Iso. Iso, you keep running in dogs and you don't learn. Stop hitting me. Throw me in one mixers. Iso, do not pick that. Iso, I swear if you pick that phone\u2014 Hello?"
      },
      {
        "name": "VURT_Love Network Jam_TT Clip 5.mp4",
        "fid": "aea2f24e-6b0d-4849-8b88-0061f58c8cab",
        "dur": 30,
        "txt": "Explain to me again how we have a problem. Really? You want to repeat what I just went through? Exactly what you went through because of your stupid decision. So explain to me how this is a we thing. Stupid? It was your idea. My what? You already look like a thief, Iso. Iso, you keep running in dogs and you don't learn. Stop hitting me. Throw me in one mixers. Iso, do not pick that. Iso, I swear if you pick that phone\u2014 Hello?"
      },
      {
        "name": "VURT_Love Network Jam_IG Clip 2 (subtitles).mp4",
        "fid": "a130717b-a363-4ff7-be51-2df48d5026fe",
        "dur": 22,
        "txt": "Be ready to move. Okay. Aha. Who is this?"
      },
      {
        "name": "VURT_Love Network Jam_IG Clip 4 (subtitles).mp4",
        "fid": "269397aa-75b8-436e-8920-2957e0e0f3a2",
        "dur": 36,
        "txt": "Kwa hivyo mslu? Kwa hivyo mslu? Kwa hivyo mslu? Kwa hivyo mslu? Kwa hivyo mslu? Kwa hivyo mslu? Kwa hivyo mslu? Kwa hivyo mslu? Kwa hivyo mslu? Kwa hivyo mslu? Kwa hivyo mslu? Kwa hivyo mslu? Kwa hivyo mslu?"
      },
      {
        "name": "VURT_Love Network Jam_TT Clip 4 (REVISED).mp4",
        "fid": "b38afcf4-c912-4908-b460-90810cfb5872",
        "dur": 36,
        "txt": "Kwa hivyo mslu? Kwa hivyo mslu? Kwa hivyo mslu? Kwa hivyo mslu? Kwa hivyo mslu? Kwa hivyo mslu? Kwa hivyo mslu? Kwa hivyo mslu? Kwa hivyo mslu? Kwa hivyo mslu? Kwa hivyo mslu? Kwa hivyo mslu? Kwa hivyo mslu?"
      },
      {
        "name": "VURT_Love Network Jam_TT Clip 5 (REVISED).mp4",
        "fid": "e968d4e9-89ef-47b6-a88e-11f3f7bab9b7",
        "dur": 30,
        "txt": "Explain to me again how we have a problem. Really? You want to repeat what I just went through? Exactly what you went through because of your stupid decision. So explain to me how this is a we thing. Stupid? It was your idea. My what? You already look like a thief, Iso. Iso, you keep running in dogs and you don't learn. Stop hitting me. Throw me in one mixers. Iso, do not pick that. Iso, I swear if you pick that phone\u2014 Hello?"
      },
      {
        "name": "VURT_Love Network Jam_TT Clip 2 (REVISED).mp4",
        "fid": "a356e7bd-9b15-4b14-987e-8f1f749487af",
        "dur": 22,
        "txt": "Be ready to move. Okay. Aha. Who is this?"
      },
      {
        "name": "VURT_Love Network Jam_IG Clip 4 (NEW).mp4",
        "fid": "745f72f7-e718-4916-8beb-c771482a9427",
        "dur": 57,
        "txt": "Crushing our faces. Yeah, and also this will make a lot of noise, you know. Then we need to bring like now, now, now. Listen up, if you make any sound once I remove this, I will slice your throat. Clear? What's your name? Is\u2014 Is\u2014 Where's your ID? Bring it, bring it. Kati beti izu. We have your ID. If we see you again, you die slowly. Slowly, yeah."
      },
      {
        "name": "VURT_Love Network Jam_IG Clip 5 (NEW).mp4",
        "fid": "c5c8fd34-700b-49b6-a2ac-d8e9ef3dc931",
        "dur": 55,
        "txt": "What? What's up? I left my phone again. Don't start, Chris. Oh, left it in Mombra. Those savages. If anyone has even touched that phone, I feel sorry for them in advance. I know, right? Can we now go? Hey. Hey, have you seen a beautiful lady in red? They left her phone. Where is it? Is this your phone? No, I found it. So you're the one who takes people's things? We go, we go, we go!"
      },
      {
        "name": "VURT_Love Network Jam_IG CliP (NEW).mp4",
        "fid": "87df9a70-7fa9-4383-86d7-1305f18e0181",
        "dur": 51,
        "txt": "Ru actually told me you got my phone back, so I came to get it. Do you really have it? Oh yes, I have it. Here it is. Ah! I'm here, you! Oh, Ezra! You really made my day. Denise, wait, Denise. This looks like a public road. Anyone could see us. Who cares? You really made me happy. Oh, Denise. Isu! Wait, what? But Isu, have you gone mad?"
      },
      {
        "name": "VURT_Love Network Jam_IG Clip 5 (APPROVED).mp4",
        "fid": "fda9e2c3-7f27-4c03-8014-74a1794b5895",
        "dur": 55,
        "txt": "What? What's up? I left my phone again. Don't start, Chris. Oh, left it in Mombra. Those savages. If anyone has even touched that phone, I feel sorry for them in advance. I know, right? Can we now go? Hey. Hey, have you seen a beautiful lady in red? They left her phone. Where is it? Is this your phone? No, I found it. So you're the one who takes people's things? We go, we go, we go!"
      },
      {
        "name": "VURT_Love Network Jam_TT Clip 5 (APPROVED).mp4",
        "fid": "d8bc87e0-918a-4280-93ba-9db424151110",
        "dur": 55,
        "txt": "What? What's up? I left my phone again. Don't start, Chris. Oh, left it in Mombra. Those savages. If anyone has even touched that phone, I feel sorry for them in advance. I know, right? Can we now go? Hey. Hey, have you seen a beautiful lady in red? They left her phone. Where is it? Is this your phone? No, I found it. So you're the one who takes people's things? We go, we go, we go!"
      },
      {
        "name": "VURT_Love Network Jam_IG CliP (NEW) SUBTITLES.mp4",
        "fid": "bd8ea6e0-01c1-441c-9ba7-9bafeb47cb87",
        "dur": 51,
        "txt": "Ru actually told me you got my phone back, so I came to get it. Do you really have it? Oh yes, I have it. Here it is. Ah! I'm here, you! Oh, Ezra! You really made my day. Denise, wait, Denise. This looks like a public road. Anyone could see us. Who cares? You really made me happy. Oh, Denise. Isu! Wait, what? But Isu, have you gone mad?"
      },
      {
        "name": "VURT_Love Network Jam_TT CliP (NEW) SUBTITLES.mp4",
        "fid": "66c0f40d-ae3d-471c-b2a4-0d8d1c55dbbd",
        "dur": 51,
        "txt": "Ru actually told me you got my phone back, so I came to get it. Do you really have it? Oh yes, I have it. Here it is. Ah! I'm here, you! Oh, Ezra! You really made my day. Denise, wait, Denise. This looks like a public road. Anyone could see us. Who cares? You really made me happy. Oh, Denise. Isu! Wait, what? But Isu, have you gone mad?"
      }
    ]
  },
  "35 & Ticking": {
    "posts": [
      {
        "id": "7628985751312534797",
        "v": 691,
        "l": 58,
        "s": 6,
        "cap": "Mike Epps is battling through the door while the neighbors listen and laugh. This is why you don't live in apartments. 35 & Ticking. Streaming free on VURT. @Mike Epps "
      }
    ],
    "clips": [
      {
        "name": "VURT_35andTicking_Social_Edit_003-v2.mp4",
        "fid": "edcda6af-0f6c-40ed-a402-7d6e4b88b44f",
        "dur": 22,
        "txt": "Man, water is water. People can taste the difference in the water, bruh. Oh, they can."
      },
      {
        "name": "VURT_35andTicking_Social_Edit_002.mp4",
        "fid": "6a852cf8-1b9c-4b77-85aa-f6f9640ce434",
        "dur": 41,
        "txt": "Hey. Oh, did you get my calls? Baby, my, um, my phone is dead, so\u2014 Couldn't you have called? I was actually worried about you. No, that I was out with my girls. Yeah, I know that, but you could have called and checked on your kids. I told you my phone is dead. And you know what? I don't\u2014"
      },
      {
        "name": "VURT_35andTicking_Social_Edit_001.mp4",
        "fid": "12f3387c-ae8e-4c70-9d6b-e9bfed98a267",
        "dur": 54,
        "txt": "You know, I'm getting really sick of you talking negative about Coco. Look, I apologize for bringing it up in front of everybody, but we can all\u2014 You know, I gotta go to the bathroom. All right. Okay, so I need to go. Fine, I'll hold it. I'll hold it. You know, everybody's marriage is different, okay? I mean, how long you and Austin been together? 2 years? No, we've been together for 3 years. Okay, 3 years. Is everything perfect? Of course not. You know, I love her, she loves me. She's a good wife and a good mother. I don't always need you and Zen looking down your nose at her. You're right. I am sorry. Do you accept my apology?"
      },
      {
        "name": "VURT_35andTicking_Social_Edit_004.mp4",
        "fid": "16c4cd11-1b1b-488e-a01b-809a1b045de7",
        "dur": 57,
        "txt": "I am so sick and tired of seeing everybody around me getting married, Harold. Like who? My cousin Shonda. Francisco married her to get a green card. What about Jameeth and Colin? Prison weddings don't work. He's doing life. Okay, what about Keisha and Carvel? He married her because your spouse can't testify against you in the court of law. How about that now? Oh, move! Don't get back! I'm not marrying you. I gotta go. You need to lose the key on that. Whatever. Yeah, you You need to go somewhere. Yeah, yeah, uh, hey, Clarice, let me get my phone. What? You got to be tripping, girl. You better give me my phone. You know what? Here, I need\u2014 take you."
      },
      {
        "name": "VURT_35andTicking_Social_Edit_005.mp4",
        "fid": "fe4c0d2c-5d63-4380-8ac9-5152c456df61",
        "dur": 26,
        "txt": "Babe, I gotta leave soon. I know you have 20 minutes for some dessert. Girl, you know I ain't got no time for that."
      },
      {
        "name": "VURT_35 and Ticking_Social Clip 1.mp4",
        "fid": "135ac1a3-89c9-4db3-be60-1866fa4efee6",
        "dur": 43,
        "txt": "You know I'm shy. Shy? Boy, you about to be 36 years old. Get off your ass and go\u2014 never mind. Excuse me. What are you doing? Hi. Oh, this is embarrassing. It's embarrassing. Yes, hi. Yes, you. Sit. This is why I don't do drinks. Oh, here she go. Okay, here she go. Get up, get up, get up. You drank too much. That's why I don't want you to\u2014 stand up. Here she come. Stand up, stand up, stand up, stand up, stand up. Sit down, sit down, sit down. Why? Sit down, 'cause you're taller than me. Tell me what to say. What to say? You ask her her name, tell her she's pretty, and don't tell her you're unemployed. Okay, I wouldn't say that because I'm not unemployed. I got a job. You know I got a job. No, you don't have a job. Yes, I do have a job. No, you don't. Shh, shh, shh. All right, look normal."
      },
      {
        "name": "VURT_35 and Ticking_Social Clip 2.mp4",
        "fid": "42397031-1450-49c1-8df9-b1bfdd3cfe0a",
        "dur": 45,
        "txt": "Hey, Z! Shaboom! Happy birthday, girl! Thank you. When we going to get some more drinks? You know what, it's Jackie's birthday too. Who's Jackie? Jackie? I'm on the phone. Oh, oh, oh, what's that? What's that? Are you talking to me? Come on now, I'm looking you right in your face, silly girl. It's a pomegranate Sockatini, okay? Hey, and how you doing? Oh, this is Victoria. Hey, Vicki! She cute. Look here, y'all, it's all upstairs. All right, come on, Pho. Come on, La. Come on, Pho."
      },
      {
        "name": "VURT_35 and Ticking_Social Clip 2 (IG - Subtitles).mp4",
        "fid": "3ae565d5-314f-4861-af80-1008f194ed75",
        "dur": 45,
        "txt": "Hey, Z! Shaboom! Happy birthday, girl! Thank you. When we going to get some more drinks? You know what, it's Jackie's birthday too. Who's Jackie? Jackie? I'm on the phone. Oh, oh, oh, what's that? What's that? Are you talking to me? Come on now, I'm looking you right in your face, silly girl. It's a pomegranate soccatini, okay? Hey, and how you doing? Oh, this is Victoria. Hey, Vicki! She cute. Look here, y'all, it's all upstairs. All right, come on, Pho. Come on, La. Come on, Pho."
      },
      {
        "name": "VURT_35 and Ticking_Social Clip 2 (TT - Subtitles).mp4",
        "fid": "8cb4dbd0-c784-49c7-a9a3-374a9ec22c58",
        "dur": 45,
        "txt": "Hey, Z! Shaboom! Happy birthday, girl! Thank you. When we going to get some more drinks? You know what, it's Jackie's birthday too. Who's Jackie? Jackie? I'm on the phone. Oh, oh, oh, what's that? What's that? Are you talking to me? Come on now, I'm looking you right in your face, silly girl. It's a pomegranate soccatini, okay? Hey, and how you doing? Oh, this is Victoria. Hey, Vicki! She cute. Look here, y'all, it's all upstairs. All right, come on, Pho. Come on, La. Come on, Pho."
      },
      {
        "name": "VURT_35 and Ticking_Social Clip 1 (IG - Subtitles).mp4",
        "fid": "6b9bcf84-7e35-4281-ae2c-66ee91d9a8b0",
        "dur": 43,
        "txt": "You know I'm shy. Shy? Boy, you about to be 36 years old. Get off your ass and go\u2014 never mind. Excuse me. What are you doing? Hi. Oh, this is embarrassing. It's embarrassing. Yes, hi. Yes, you. Sit. This is why I don't do drinks. Oh, here she go. Okay, here she go. Get up, get up, get up. You drank too much. That's why I don't want you to\u2014 stand up. Here she come. Stand up, stand up, stand up, stand up, stand up. Sit down, sit down, sit down. Why? Sit down, 'cause you're taller than me. Tell me what to say. What to say? You ask her her name, tell her she's pretty, and don't tell her you're unemployed. Okay, I wouldn't say that because I'm not unemployed. I got a job. You know I got a job. No, you don't have a job. Yes, I do have a job. No, you don't. Shh, shh, shh. All right, look normal."
      },
      {
        "name": "VURT_35 and Ticking_Social Clip 1 (TT - Subtitles).mp4",
        "fid": "0e791be9-3769-4323-90cf-53f1507de93c",
        "dur": 43,
        "txt": "You know I'm shy. Shy? Boy, you about to be 36 years old. Get off your ass and go\u2014 never mind. Excuse me. What are you doing? Hi. Oh, this is embarrassing. It's embarrassing. Yes, hi. Yes, you. Sit. This is why I don't do parties. Oh, here she go. Okay, here she go. Get up, get up, get up. You drank too much. That's why I don't want you to\u2014 stand up. Here she come. Stand up, stand up, stand up, stand up, stand up. Sit down, sit down, sit down. Why? Sit down, 'cause you're taller than me. Tell me what to say. What to say? You ask her her name, tell her she's pretty, and don't tell her you're unemployed. Okay, I wouldn't say that because I'm not unemployed. I got a job. You know I got a job. No, you don't have a job. Yes, I do have a job. No, you don't. Shh, shh, shh. All right, look normal."
      },
      {
        "name": "VURT_35 and Ticking_Social Clip 3.mp4",
        "fid": "b90f72d0-cf31-4c4b-985f-90d5e020a44f",
        "dur": 31,
        "txt": "Listen, I gotta go, guys. Why do you have to go? I gotta pick the kids up, right? This is the worst birthday ever. Oh, you're not leaving 'cause of me, are you? Stop it, Vic. Okay. Look, why can't Coco pick them up? It's my birthday. Look out. Yeah, Coco is\u2014 What's wrong with him? That's Phil's wife."
      },
      {
        "name": "VURT_35 and Ticking_Social Clip 4.mp4",
        "fid": "89332a79-608f-4b6c-be2a-9a8e78cd44de",
        "dur": 61,
        "txt": "Oh, that poor little honey. He is never going to find anyone, ever. You feel bad for him? I do. Well, you should feel bad for me because I'm never going to find anyone. OK, yes you will, Zenobia. No, I'm not. Look around. This place is full of men and absolutely no prospects for me. I'm knocking on 40's door and\u2014 do you hear that? Girl, yes, that's my song. No, no. Hey. Not the song. Do you hear the clock ticking? Do you hear it? Okay, you are really\u2014 It's my biological clock. It's ticking, Victoria, and I just\u2014 You're being silly. No, I'm not. Yes, you are. You know, I'm not trying to have any kids at 40 years old. I'll take my kids to nursery school and they're gonna say, \"Is that your grandmama?\" It's not cute."
      },
      {
        "name": "VURT_35 and Ticking_Social Clip 5.mp4",
        "fid": "2bda44e2-a2c1-4f6b-97c0-dd2ebebdf97e",
        "dur": 61,
        "txt": "I just walked in the door. Can I at least just get some time to\u2014 You know something, stop. Can I just please just get some time to get situated? Take your time. All the time you need. Take all the time you need. Oh, goodness. Your dead phone is ringing. Baby, I'm too tired to talk. The phone you told me was dead is ringing. Who the hell's calling you at 2:30 in the morning? Can we please talk about this in the morning? I'm too tired. Too tired."
      },
      {
        "name": "VURT_35 and Ticking_Social Clip 6.mp4",
        "fid": "44ca2729-870a-4cc1-b0c8-79d6c2788bb4",
        "dur": 55,
        "txt": "Really? Really? Calm down, girl. You know you too pretty to be all mad and angry like that. We really should go out sometime. Jimmy! No, no, no, hold up, girl. Why you got to be all like that? What are we, about 5'10\", 5'11\"? I mean, we could make a cold team, girl. You know what? You don't need to say another other word to me. Why you got to be like that? Girl, we could have a starting five. I'll put a nice little power forward right all up\u2014 Hey, hold up! What's that? Put your hands down! What the hell wrong with you? I know this triac didn't just slap Nick West! Did y'all get that on films? Did y'all get that? Hold up, man. What the hell you gonna do? Back up, man! You see this? You see this gator? Endangered species, and it will bite your ass. I got a shoe too. I got a shoe too. You and the rest of the Skittles need to get up out of here."
      }
    ]
  },
  "Something Like A Business": {
    "posts": [
      {
        "id": "7629717736997817614",
        "v": 305,
        "l": 20,
        "s": 0,
        "cap": "Avery. Not Ovary. Avery. Donnell Rawlings had a whole character built around people mispronouncing his name and it still hits. Something Like A Business. Free on VURT. @Kevin Hart @Donnell Rawlings @Leslie Jones  #VURT #SomethingLikeABusiness #DonnellRawlings #KevinHart #LeslieJones"
      },
      {
        "id": "7629362191732346126",
        "v": 691,
        "l": 67,
        "s": 7,
        "cap": "Uncle 3D turned a little league pep talk into a whole coaching session. Just not for baseball. Something Like A Business. Streaming free on VURT. @Kevin Hart @David Alan Grier  #VURT #SomethingLikeABusiness #DavidAlanGrier #KevinHart #Comedy  "
      },
      {
        "id": "7628690331508149517",
        "v": 569,
        "l": 54,
        "s": 8,
        "cap": "She just told the judge he was a client. In open court. With the duck head and everything. Something Like A Business. Streaming free on VURT. @Kevin Hart @tasha4realsmith1 @Keith David @Leslie Jones @Kym Whitley @Donnell Rawlings @\u15f4\u15e9\u1587T\u157c\u146b\u144c\u15e9K\u15f4 @J. Anthony Brown  #VURT #SomethingLikeABusiness #KevinHart #DramaTok #ComedyMovie "
      },
      {
        "id": "7626398764424498446",
        "v": 380000,
        "l": 777,
        "s": 99,
        "cap": "He tried to stand up for himself. She stood him back down. Something Like A Business. Free on VURT. Myvurt.com @Kevin Hart  #VURT #SomethingLikeABusiness #KevinHart #ComedyTok #MicroDrama "
      }
    ],
    "clips": [
      {
        "name": "SomethingLikeBusiness-1.mp4",
        "fid": "a7e2b582-a6fa-44b2-a24a-3dfcc61dbfbf",
        "dur": 36,
        "txt": "Call me out of my name again. Say it again. To her face? Say it again. Okay. Oh, you must think it's a game. I said I'm\u2014 Oh, Jesus. Okay, watch it. Okay, um, give me half of it if you want. I don't even mind getting a half. Okay, um, you got a check? If a check\u2014 a check would do for real. Okay, that's the one. Okay. I think I'm singing better. Did I do good though? To the best of my ability. Where's more? Oh, Jesus."
      },
      {
        "name": "SomethingLikeBusiness-3.mp4",
        "fid": "8b567778-c51b-4cee-bf35-8cae69627bbd",
        "dur": 61,
        "txt": "Chocho, why you crying? I struck out. That's okay, all true ballers strike out every now and then. You can't let that slow your roll. You gotta pick up that pimp stick and keep on swinging. That's right, Chocho. Right? Yes. I still remember the first time I struck out on you. I remember too. But I knew if I was gonna score\u2014 Back up! You better back up! But I knew if I was gonna score, I had to make it to first. So I got my grill right, my rap tight, and Blop, blip, blam, blue, and pa! What happened, baby? First base! Look like I'm about to steal second. I'm about to steal second. Oh, I'm in second round in the third. We're third, baby. Oh, we about to slide in the hole face first. Spike time! Safe, safe, safe. Game over. Oh, you coming to the after party, JoJo?"
      },
      {
        "name": "SomethingLikeBusiness-7.mp4",
        "fid": "123e3353-9c70-4460-989e-ed14a679e20d",
        "dur": 56,
        "txt": "Can I ask you a question, Judge Trey? Can you, with a clear conscience, sleep at night, Judge Trey, knowing that you have broken up a happy family? So please, Judge Trey, don't judge this book by its cover. I'm a mom on the inside, Judge Trey, but all you see is a hoe. And it's the same hoe that you came to visit on Minnesota Avenue at 2 o'clock in the morning and had me wearing a mascot head of a duck as part of your kinky little fetishes. I don't want no damn duck head in my life. What? I'm wearing slippers. These are slippers. I bought these at Duckworth. Can a man wear slippers if you want him to slip?"
      },
      {
        "name": "Something_Like_Business_v1_Social 02_1.mp4",
        "fid": "ed3a4bf3-f63d-49c8-920c-83971efbd0a5",
        "dur": 63,
        "txt": "You buy now, you leave. I don't know what I want yet. All right, the strawberry coolness. Do it really taste like strawberry, or is it, is it like strawberry? I had some before and it wasn't really that strawberry. Okay, um. The banana daiquiri mix. Does it really taste like bananas? It taste like banana. But is it the bananiest? 'Cause they don't always\u2014 I do not have all day for you. I want a bananary tasting daiquiri. That's what I want. You fucking making me sick. You know what? Just give me some beer. Is it beer-berry? It's not the beeriest? Go, go, go, go, go! Is this beer? Is\u2014 am I going to get drunk?"
      },
      {
        "name": "Something_Like_Business_v1_Social 03_1.mp4",
        "fid": "f7342ae7-47f6-4c56-8ce1-1b88c23ce89c",
        "dur": 59,
        "txt": "What we gonna do, y'all? I know, I know what to do, y'all. Run, run, run! Go, go! You order! You order now! You get the same thing every night. Shrimp fried rice. Well, I might want something different today, all right? Uh, what's in the, uh, chicken teriyaki? Chicken! You know it's chicken. What's in the broccoli and shrimp? What? You want ovary? My name is Avery, not ovary. You know my name is Avery. Just give me the shrimp fried rice. You make me sick. Ah!"
      },
      {
        "name": "Something_Like_Business_v1_Social 01_1.mp4",
        "fid": "0f9181c1-f613-403e-b79f-3eadcd1ac9b9",
        "dur": 74,
        "txt": "Judge Joseph A. Purgatory will be presiding over these proceedings. This is a case of The State versus Angela A. Rockamore. Hey y'all! That's Judge Trey from TV? Judge Trey?! Yeah! J.J.! J.J.! J.J.! Okay, okay, order in the court. Y'all take your seats. Okay, let's see what we've got here\u2014 We've got prostitution and child endangerment. I detest any woman, any woman who engages in sex for sale. Prostitution is illegal in the District of Columbia. Exposing your children to that lifestyle, that is despicable. However, I am just here to judge these proceedings. We have selected a jury of your peers who we think will be objective, unbiased, and fair. Bailiff, can you bring in the jury?"
      }
    ]
  },
  "Schemers": {
    "posts": [],
    "clips": [
      {
        "name": "Kevin Spence_IMG_0748.MOV",
        "fid": "d09026e9-4b76-49e0-b18a-2849a7689935",
        "dur": 20,
        "txt": "Hey, what's up everybody? It's your boy, producer K Spence, Spence World Studios. One of the executive producers of the movie Schemers, along with my partner in crime, my brother Courtney. Hey, Schemers is streaming right now on VIRT. Check it out, Schemers, VIRT. Check it out, it's streaming right now. Go check it out. Trina, Safaree, Donna, Fredro Starr, Omar Gooding, all on VIRT right now. Check it out, Schemers."
      },
      {
        "name": "Antwan Smith_IMG_7830.mov",
        "fid": "b1207fbe-ccba-4f74-9fcf-e90bb27f539a",
        "dur": 28,
        "txt": "All right, rolling. All right, 3, 2, 1. What's up everybody, this is Director Antoine Smith, the director of Schemers. Check us out on VRT right now, V-U-R-T, VRT. Download the app to your phone and catch 24 episodes of flaming hot Schemers. Also check out their, um, Instagram page @myvert and support them. Appreciate y'all. Keep Schemers number one."
      },
      {
        "name": "Swurv and Trina Drop.mov",
        "fid": "c83e192d-feb2-4881-8643-392ed5ba279e",
        "dur": 19,
        "txt": "Man, y'all know who I'm talking about. Y'all know what I'm talking about. I'm talking about Schemers, man. It's a movie. The movie. Biggest movie. Number one right now. Popular. And I'm in the movie. Yeah."
      },
      {
        "name": "VURT_Schemers_Social_001.mp4",
        "fid": "2bf04195-e7a4-4ba0-aad3-6860552a5ed0",
        "dur": 78,
        "txt": "Larry, baby, what's up? I'm here. I need a bottle of Crown. What you got for me? Oh, hey, Chris, what's up, baby? What's going on? Actually, give me a bottle of Henny. The biggest bottle you got. The biggest one I got? Thank you. Girl, you got money today. Hold on, let me check this here. What you say you want? I don't wanna check it. What you want? Crown and the biggest bottle of Henny you got. Goddamn, wait a minute. This money say motion picture. What the fuck? And George Washington's head is bent on this motherfucker. Girl, that's counterfeit money. Get the hell outta here. Come on. Get your money. You gonna make me call them crackers on you. Go on, get your money. Go on, go on out of here. Fuck. You ain't gonna get nobody no fake pussy. Why you gonna come here and give up fake money? This motherfucker, Larry, shut up. You should have been a dog when you was a baby. I don't understand. Why we going back to the motel? That Hector dude from the motel? Yeah. He paid me with fake money. He paid you with fake money? I don't understand. How he pay you with fake money? Fake money? Come on, man. Motion pictures."
      },
      {
        "name": "VURT_Schemers_Social_002.mp4",
        "fid": "a6a1c386-f933-41f7-8be2-f2364635e616",
        "dur": 55,
        "txt": "Oh my God, Chrissy, what do I do? Calm down. What I need for you to do is breathe. Breathe. Okay, I am tranquila, pero qu\u00e9 hago? All right, where are you? I'm in the kitchen. And where is he? I don't know, he's like letting guests out or something. All right, perfect. Then you got a few minutes to make this work. I need to find a way for you to get out that dress. Grab that bottle of wine or something. Act like you spilled it on yourself. No way. I put this dress on my credit card. There's no way I'm doing that. What the fuck is that? Listen, get your head in the game and fuck that dress up. No, no. How am I going to ruin this perfectly beautiful dress? So you have a legitimate reason to be butt-ass naked when he finds you. Okay."
      },
      {
        "name": "VURT_Schemers_Social_003.mp4",
        "fid": "cfb8d3bb-a770-4729-8fa8-f2bc8b4e2e6f",
        "dur": 64,
        "txt": "Show me what you got, boss lady. We have all of these. Wow, wow. I have these too. Sheesh, it's nice. Oh, diamonds, ice. So how much you want for all of this? Um, I don't know, how much you offering? Watches, chains, say about $50K. For the diamonds, $40,000, $45,000. Bullshit. This watch alone here is $40,000. Yeah, but these watches got serial numbers. Nitronic and knock. I gotta melt these shits down. And these diamonds, shit, they cloudy. What you want from me? A better offer. Well, bring me some better merchandise, baby girl. Fuck you."
      },
      {
        "name": "VURT_Schemers_Social_004.mp4",
        "fid": "44028123-148d-4dcf-a73a-7fc4a7f33a27",
        "dur": 66,
        "txt": "Wait until you try this baby chick. What the fuck? Oh yeah, y'all done ran up on the wrong ones today. Sorry to startle you ladies, but you need to calm down right now. Okay, who the fuck are you and what the fuck do you want? So you're the one that's named Chrissy, right? How the fuck you know my name? How do I know she name? You heard her? She said how do I know her name? People like you talk too much and it's too loud and so obvious, but you want to act like no one see you. I know all of you more than you know your damn self. Isn't your name Chrissy, the other one Jasmine, and the other one Antoinette? You don't know shit. Desperate people like you. You're the type of person who is obsessed of being rich because you're too scared of being poor."
      },
      {
        "name": "VURT_Schemers_Social_005.mp4",
        "fid": "953de5f2-78fe-4279-baef-75206f992632",
        "dur": 68,
        "txt": "I mean, it's a beautiful day. What you think? Because this week I'm good, all right? Hey, I have to call you back, man. Oh, shit! Get up, man! Get up! Hello? Go! Go!"
      },
      {
        "name": "VURT_Schemers_Social_006.mp4",
        "fid": "71351784-ecf5-4595-b5c0-ab5b88ee7636",
        "dur": 57,
        "txt": "Yo, bro, you know better than to call me from your personal phone. You smoking crack? It's the girls, man. Look, Nene was on the phone with Renee. A dude ran up on them. She heard screaming. The call dropped. Now we can't reach them. Yo, chill. Take a breath. You don't know anything yet. Look, this wasn't us, was it? I thought we deaded that shit years ago. I got out. Look, I warned you. There's no such thing as being out. But those niggas know better. I don't give a fuck who it is. But they gonna find out they fucked with the wrong family. I'm on the next flight. Alright."
      },
      {
        "name": "VURT_SCHEMERS_TRAILER_Social_Edit_001.mp4",
        "fid": "5961a376-46cf-4fee-b047-51ab406b191d",
        "dur": 19,
        "txt": "Look at how much money is here one more time. This is just one account. Let's get this money. One, two, three."
      },
      {
        "name": "VURT_SCHEMERS_TRAILER_Social_Edit_002.mp4",
        "fid": "d5e12e4c-571c-425c-a46d-d2b5f306b655",
        "dur": 38,
        "txt": "Trina, I got money habits. Hell, you got money today. This money say motion picture, what the fuck, and George Washington. Motion picture, let me\u2014 You gonna make me call them crackers on you. Go on, get your money and go. Get your money and go, go on. Roll outta here. Greasy. Okay, so what happened? You were so happy like 5 minutes ago. I did all type of wild shit with this nigga. He gave me counterfeit money."
      },
      {
        "name": "VURT_SCHEMERS_TRAILER_Social_Edit_003.mp4",
        "fid": "674ad9bd-f1df-4287-b6e2-40bc80176c83",
        "dur": 32,
        "txt": "You can't be happy at that raggedy-ass office making how much you up to now? $13, $14 an hour? And you bitch, you flipping cell phones and laptops while your boss driving the form. We were up all night talking about what you said. Not the stuff about Colombia, which was racist by the way. Get to the point. You know what, Chrissy? You're right. We really hate this check-to-check stuff, but what else is there?"
      },
      {
        "name": "VURT_SCHEMERS_TRAILER_Social_Edit_004.mp4",
        "fid": "4d90824b-0d07-474f-813a-ba3b782c0557",
        "dur": 46,
        "txt": "I see different type of bitches at the clubs all the time, but the ones that seem to be doing quite well for themselves are the ones that don't even work there. They lure these clown ass niggas back to the hotel or back home and then boom. I want you to meet Frank. He's in banking. What is he, a teller? No, my dear. I am the regional manager for Banco Atlantico. We hitting bars, clubs, casinos, lounges, all the spotterinas where the real money be at. Baddest bitches, all them got BBLs, just took your nigga attention to that."
      },
      {
        "name": "VURT_SCHEMERS_TRAILER_Social_Edit_005.mp4",
        "fid": "336e99ad-bac9-4bd8-a101-b120ae4f61de",
        "dur": 46,
        "txt": "Neck, lady ass, and thighs match. Take a picture from the front and you can see it from the back. Give me a corporate nigga. I'm talking major black gold potential. But that's peanuts. These guys are loaded. You don't know shit. Desperate people like you. You're the type of person who is obsessed of being rich because you're too scared of being poor. 4. But see, people like me know what they're doing and do things well. It's done."
      },
      {
        "name": "VURT_SCHEMERS_TRAILER_Social_Edit_006.mp4",
        "fid": "a71a2011-01e1-4a16-88d5-bf0ce1bf7950",
        "dur": 62,
        "txt": "Look, this wasn't us, was it? I thought we deaded that shit years ago. I got out. Look, I warned you. There's no such thing as being out. Those niggas know better. I don't give a fuck who it is, but they gonna find out they fucked with the wrong family. This nigga just paid me in counterfeits, and I'm not finna let it happen again. See, you too negative. You all fucked up. Something happened. I don't know. I got money habits. This Chanel tote gonna cost you. One second. Good. Look at me. I did this to you."
      }
    ]
  },
  "Bride To Be": {
    "posts": [
      {
        "id": "7631420357089430798",
        "v": 94,
        "l": 1,
        "s": 1,
        "cap": "The director came on to tell you herself. Bride to Be. Streaming free on VURT. @starraeproductions #BrideToBe #VURT #IndieFilm #FilmTok"
      }
    ],
    "clips": [
      {
        "name": "B2B Racheal Leigh VURT Vertical.mov",
        "fid": "526b10a1-6741-407e-a6b3-df949a7e5e50",
        "dur": 20,
        "txt": "Hi, I'm Rachel Lee from Star Ray Productions in Australia. I am the producer, director, and editor of Brandy Self's Bride to Be. It is a 3-part series which I'm very excited to say is now available to stream on Vert, so make sure you download the app and check it out."
      },
      {
        "name": "B2B Stephanie Lightman VURT Vertical.mp4",
        "fid": "f24c14b4-6e11-4aaf-98a6-04986117af5c",
        "dur": 11,
        "txt": "Hi guys, my name is Stephanie Lightman and I play Nina in the movie Bride to Be, now streaming on Vert."
      },
      {
        "name": "VURT_Bride To Be_Social Clip 1.mp4",
        "fid": "e941e5f0-d4e8-4e72-9e03-8f7b4eef6966",
        "dur": 60,
        "txt": "I just want everything to be perfect, you know? A girl waits her whole life for her wedding day. I hope Erica likes the dress. Erica? Of course, Erica. She's going to love it. I bet you she can't wait to see me in it. Not bad. Is it really me? I must have tried on a million dresses. Pearl, eggshell, alabaster, chiffon, charmeuse, lace. But I think this is the first time I really feel like a bride. Put the veil on, would you? So I can see it all together. Wait! What about the veil? I want to see!"
      },
      {
        "name": "VURT_Bride To Be_Social Clip 2.mp4",
        "fid": "108e87d8-6641-4a00-9c5a-7f93dbca0cd2",
        "dur": 37,
        "txt": "Erica! It's bad luck to see the dress before the wedding. She's right. Promise to keep my eyes closed if I can get some sugar from my bride. Here. You are. What are you doing? I can't believe I get to marry the love of my life in just over 48 hours. How lucky am I? I'm the lucky one. What? No, I'm the one who's supposed to be getting married."
      }
    ]
  }
}